fabric_analytics_mcp/__init__.py
fabric_analytics_mcp/cli.py
fabric_analytics_mcp/server_manager.py
fabric_analytics_mcp-1.0.2.dist-info/METADATA
fabric_analytics_mcp-1.0.2.dist-info/WHEEL
fabric_analytics_mcp-1.0.2.dist-info/entry_points.txt
fabric_analytics_mcp-1.0.2.dist-info/top_level.txt
fabric_analytics_mcp-1.0.2.dist-info/RECORD
