Metadata-Version: 2.4
Name: fabric-analytics-mcp
Version: 1.0.2
Summary: Microsoft Fabric Analytics MCP Server - Enable AI assistants to access and analyze Microsoft Fabric data
Home-page: https://github.com/santhoshravindran7/Fabric-Analytics-MCP
Author: Santhosh Ravindran
Author-email: santhoshravindran7@gmail.com
Project-URL: Bug Tracker, https://github.com/santhoshravindran7/Fabric-Analytics-MCP/issues
Project-URL: Documentation, https://github.com/santhoshravindran7/Fabric-Analytics-MCP#readme
Project-URL: Source Code, https://github.com/santhoshravindran7/Fabric-Analytics-MCP
Keywords: mcp,model-context-protocol,microsoft-fabric,analytics,data-analysis,llm,ai,claude,copilot,spark,livy,authentication,azure,powerbi,data-science
Classifier: Development Status :: 5 - Production/Stable
Classifier: Intended Audience :: Developers
Classifier: Intended Audience :: Science/Research
Classifier: Topic :: Software Development :: Libraries :: Python Modules
Classifier: Topic :: Scientific/Engineering :: Artificial Intelligence
Classifier: Topic :: Database :: Database Engines/Servers
Classifier: License :: OSI Approved :: MIT License
Classifier: Programming Language :: Python :: 3
Classifier: Programming Language :: Python :: 3.8
Classifier: Programming Language :: Python :: 3.9
Classifier: Programming Language :: Python :: 3.10
Classifier: Programming Language :: Python :: 3.11
Classifier: Programming Language :: Python :: 3.12
Classifier: Operating System :: OS Independent
Classifier: Environment :: Console
Requires-Python: >=3.8
Requires-Dist: click>=8.0.0
Requires-Dist: requests>=2.25.0
Requires-Dist: packaging>=20.0
Requires-Dist: setuptools>=40.0
Provides-Extra: dev
Requires-Dist: pytest>=6.0; extra == "dev"
Requires-Dist: pytest-cov>=2.0; extra == "dev"
Requires-Dist: black>=21.0; extra == "dev"
Requires-Dist: flake8>=3.8; extra == "dev"
Requires-Dist: mypy>=0.800; extra == "dev"
Provides-Extra: async
Requires-Dist: aiohttp>=3.8.0; extra == "async"
Requires-Dist: asyncio>=3.4.3; extra == "async"
Dynamic: author
Dynamic: author-email
Dynamic: classifier
Dynamic: description
Dynamic: description-content-type
Dynamic: home-page
Dynamic: keywords
Dynamic: project-url
Dynamic: provides-extra
Dynamic: requires-dist
Dynamic: requires-python
Dynamic: summary
